threalestate/__init__.py
threalestate/connectors/__init__.py
threalestate/connectors/mysql_connector.py
threalestate/connectors/redis_connector.py
threalestate.py-0.0.1.dist-info/DESCRIPTION.rst
threalestate.py-0.0.1.dist-info/METADATA
threalestate.py-0.0.1.dist-info/RECORD
threalestate.py-0.0.1.dist-info/WHEEL
threalestate.py-0.0.1.dist-info/metadata.json
threalestate.py-0.0.1.dist-info/top_level.txt
